LICENSE
MANIFEST.in
README.md
README.rst
setup.py
banditvis/__init__.py
banditvis/__main__.py
banditvis/algorithms.py
banditvis/animation.py
banditvis/arms.py
banditvis/core.py
banditvis/data.py
banditvis/defaults.py
banditvis/formatting.py
banditvis/helper.py
banditvis/manager.py
banditvis/parse.py
banditvis/plot.py
banditvis/simulation.py
banditvis.egg-info/PKG-INFO
banditvis.egg-info/SOURCES.txt
banditvis.egg-info/dependency_links.txt
banditvis.egg-info/entry_points.txt
banditvis.egg-info/not-zip-safe
banditvis.egg-info/requires.txt
banditvis.egg-info/top_level.txt
tests/__init__.py
tests/test_core.py