Metadata-Version: 1.1
Name: banditvis
Version: 0.9
Summary: A library for simulating and visualizing bandit algorithms.
Home-page: https://github.com/alexrutar/banditvis
Author: Alex Rutar
Author-email: arutar@uwaterloo.ca
License: MIT
Keywords: bandit machine learning
Platform: UNKNOWN
Classifier: Development Status :: 3 - Alpha
Classifier: Programming Language :: Python :: 3.6
Classifier: License :: OSI Approved :: MIT License
